{
  "entry": "server.js",
  "files": {
    "0ce6cb91788b0d154899.js": "0ce6cb91788b0d154899.js",
    "0ec714b4aebf191bb1d5.js": "0ec714b4aebf191bb1d5.js",
    "2e5da77e28aff0087e1c.js": "2e5da77e28aff0087e1c.js",
    "3eecc9041487d6c3c8fa.js": "3eecc9041487d6c3c8fa.js",
    "75f2fdf33aa96f1e68df.js": "75f2fdf33aa96f1e68df.js",
    "93f90ea44762ff13ddd5.js": "93f90ea44762ff13ddd5.js",
    "a0861c1fb858ca9c7904.js": "a0861c1fb858ca9c7904.js",
    "e81b9ccd747401afdee1.js": "e81b9ccd747401afdee1.js",
    "server.js": "server.js"
  },
  "maps": {}
}